khard/__init__.py
khard/__main__.py
khard/actions.py
khard/address_book.py
khard/cli.py
khard/config.py
khard/contacts.py
khard/exceptions.py
khard/formatter.py
khard/khard.py
khard/query.py
khard/version.py
khard/data/config.spec
khard/data/template.yaml
khard/helpers/__init__.py
khard/helpers/interactive.py
khard/helpers/typing.py
khard-0.20.1.dist-info/licenses/LICENSE
khard-0.20.1.dist-info/METADATA
khard-0.20.1.dist-info/WHEEL
khard-0.20.1.dist-info/entry_points.txt
khard-0.20.1.dist-info/top_level.txt
khard-0.20.1.dist-info/RECORD
