Metadata-Version: 2.4
Name: khard
Version: 0.20.1
Summary: A console address book manager
Author-email: Eric Scheibler <email@eric-scheibler.de>
License: GPL
Project-URL: homepage, https://github.com/lucc/khard
Project-URL: documentation, https://khard.readthedocs.io/en/latest/
Project-URL: repository, https://github.com/lucc/khard.git
Project-URL: changelog, https://github.com/lucc/khard/blob/main/CHANGES
Keywords: vcard,console,addressbook
Classifier: Development Status :: 4 - Beta
Classifier: Environment :: Console
Classifier: Topic :: Utilities
Classifier: Topic :: Communications :: Email :: Address Book
Classifier: License :: OSI Approved :: GNU General Public License (GPL)
Classifier: Intended Audience :: End Users/Desktop
Classifier: Operating System :: POSIX
Classifier: Programming Language :: Python :: 3 :: Only
Requires-Python: >=3.9
License-File: LICENSE
Requires-Dist: configobj==5.*,>=5.0.6
Requires-Dist: ruamel.yaml>=0.17.0
Requires-Dist: vobject~=0.9.7
Provides-Extra: doc
Requires-Dist: sphinx; extra == "doc"
Requires-Dist: sphinx-argparse; extra == "doc"
Requires-Dist: sphinx-autoapi; extra == "doc"
Requires-Dist: sphinx-autodoc-typehints; extra == "doc"
Provides-Extra: typing
Requires-Dist: mypy; extra == "typing"
Dynamic: license-file
